prioqueue/__init__.py
prioqueue-0.1.0.dist-info/METADATA
prioqueue-0.1.0.dist-info/WHEEL
prioqueue-0.1.0.dist-info/licenses/LICENSE
prioqueue-0.1.0.dist-info/RECORD
